colorway_background.py
colorway_foreground.py
colorway_manual.py
colorway-2.0.0.dist-info/LICENSE
colorway-2.0.0.dist-info/METADATA
colorway-2.0.0.dist-info/WHEEL
colorway-2.0.0.dist-info/top_level.txt
colorway-2.0.0.dist-info/RECORD
