Metadata-Version: 2.1
Name: colorway
Version: 2.0.0
Summary: Python package to change the text color of the python console.
Home-page: https://github.com/xhelphin/colorway
Author: Jack Greenacre
Author-email: jaxk.programmer@gmail.com
Classifier: Programming Language :: Python :: 3
Classifier: Programming Language :: Python :: 3.6
Classifier: Programming Language :: Python :: 3.7
Classifier: Programming Language :: Python :: 3.8
Classifier: Programming Language :: Python :: 3.9
Classifier: Programming Language :: Python :: 3.10
Classifier: License :: OSI Approved :: GNU General Public License v3 (GPLv3)
Classifier: Operating System :: OS Independent
License-File: LICENSE
Provides-Extra: dev
Requires-Dist: pytest (>=3.7) ; extra == 'dev'
Requires-Dist: check-manifest (>=0.48) ; extra == 'dev'
Requires-Dist: twine (>=3.8.0) ; extra == 'dev'
